njet/__init__.py
njet/_version.py
njet/ad.py
njet/common.py
njet/extras-Copy1.py
njet/extras-Copy2.py
njet/extras.py
njet/functions.py
njet/jet-Copy1.py
njet/jet.py
njet/poly.py
njet-0.5.2.dist-info/LICENSE.txt
njet-0.5.2.dist-info/METADATA
njet-0.5.2.dist-info/WHEEL
njet-0.5.2.dist-info/top_level.txt
njet-0.5.2.dist-info/RECORD
