Metadata-Version: 2.1
Name: njet
Version: 0.5.2
Summary: Lightweight automatic differentiation package for higher-order differentiation.
Author: Malte Titze
Author-email: mtitze@users.noreply.github.com
License: GPL-3.0-or-later
Project-URL: homepage, https://njet.readthedocs.io/en/latest/index.html
Project-URL: repository, https://github.com/mtitze/njet
Keywords: AD jet njet automatic differentiation
Requires-Python: <3.11,>=3.8
License-File: LICENSE.txt
Requires-Dist: numpy (==1.*,>=1.21.2)
Requires-Dist: sympy (==1.*,>=1.8.0)
Requires-Dist: more-itertools (==9.*,>=9.0.0)
Requires-Dist: tqdm (==4.*,>=4.64.0)
Provides-Extra: dev
Requires-Dist: ipykernel (==6.*,>=6.4.1) ; extra == 'dev'
